async_sqlserver_lib/__init__.py
async_sqlserver_lib/db_manager.py
async_sqlserver_lib/decorators.py
async_sqlserver_lib-1.0.3.dist-info/LICENSE
async_sqlserver_lib-1.0.3.dist-info/METADATA
async_sqlserver_lib-1.0.3.dist-info/WHEEL
async_sqlserver_lib-1.0.3.dist-info/top_level.txt
async_sqlserver_lib-1.0.3.dist-info/RECORD
