Metadata-Version: 2.1
Name: async-sqlserver-lib
Version: 1.0.3
Summary: A Python library for managing asynchronous SQL Server connections.
Home-page: https://github.com/brandaolu94s/async-sqlserver-lib
Author: Lucas Brandão
Author-email: lbsantos@bencorp.com.br
License: MIT
Keywords: sql-server asyncio sqlalchemy aioodbc
Classifier: Programming Language :: Python :: 3.12
Classifier: License :: OSI Approved :: MIT License
Classifier: Operating System :: OS Independent
Requires-Python: >=3.8
License-File: LICENSE
Requires-Dist: setuptools
Requires-Dist: wheel
Requires-Dist: sqlalchemy[asyncio]>=1.4
Requires-Dist: aioodbc>=0.2.6
Requires-Dist: python-dotenv>=0.21.0
Provides-Extra: dev
Requires-Dist: pytest; extra == "dev"
Requires-Dist: pytest-asyncio; extra == "dev"
